acnh
