Metadata-Version: 1.1
Name: acnh
Version: 1.0
Summary: Dataset containing fish, fossils, bugs, etc for Animal Crossing: New Horzions
Home-page: https://github.com/valknight/ACNH-Dataset
Author: Val Knight
Author-email: val@valknight.xyz
License: MIT license
Platform: UNKNOWN
Classifier: Development Status :: 1 - Planning
Classifier: Intended Audience :: Developers
Classifier: License :: OSI Approved :: MIT License
Classifier: Programming Language :: Python :: 3
Classifier: Programming Language :: Python :: 3.7
